{"name":"Kontrollsystem: EA DRIFTSKONTROLL","description":"EA driftskontroll er et system for styring og overvåkning av vann og avløp. Dette inkluderer styring og overvåkning av omtrent 180 lokasjoner innen vann og 140 lokasjoner tilknyttet avløp med følgende for funksjoner:  Vann/høydebasseng  Vann/pumpestasjoner  Vann/ledningsnett  Avløp/pumpestasjoner  Avløp/ledningsnett ","integrations":["MDA","EA6","EA6 sekundær","PaneIPC","TKAVPN","HSRP"],"Virksomhetsområde":"Byutvikling","klasse":"Annet","delsystem type":"NA"}