{"Name":"ServiceNow Enhet for kommunikasjon, administrasjon og innbyggerkontakt","Description":"Saksbehandlingsverkt\u00F8y for kundeservice ved Enhet for kommunikasjon, administrasjon og innbyggerkontakt ","ADGroup":"Appl-SN_kundeservice Enhet for kommunikasjon, administrasjon og innbyggerkontakt\nAppl-SN_kundeservice Ledergruppa Enhet for kommunikasjon, administrasjon og innbyggerkontakt","ImportantNotes":"I feltet \u0022Tilgang til andre fagsystemer/programmer\u0022 skriver enheten \u0022Kundeservice Enhet for kommunikasjon, administrasjon og innbyggerkontakt\u0022/\u0022Ledergruppa Enhet for kommunikasjon, administrasjon og innbyggerkontakt\u0022\n\n","SoftwareModelForBA":null,"WhoCanOrder":null,"ForwardNew":null,"ForwardDelete":null,"Adress":null,"datasource":"Programoversikt.xlsx"}