{"Name":"VISMA Flyt PPT","Description":"Visma Flyt er det nye saksbehandlingsprogrammet for PPT (BFT) og PPT for voksne (erstatter PPI). ","ADGroup":"Appl-VismaFlytPPT\nAppl-VismaFlytPPT-Admin","ImportantNotes":"Tjenesteforvalter: Maj-Britt Nilsen\nmaj-britt.nilsen@trondheim.kommune.no\n\nTjenesteforvalter m\u00E5 ha f.nr og ansatt ID","SoftwareModelForBA":"Ja","WhoCanOrder":null,"ForwardNew":"x","ForwardDelete":"x","Adress":"Acos-ppi.Postmottak@trondheim.kommune.no","datasource":"Programoversikt.xlsx"}